Final2x_core/SRclass.py
Final2x_core/SRqueue.py
Final2x_core/__init__.py
Final2x_core/__main__.py
Final2x_core/config.py
Final2x_core/util/__init__.py
Final2x_core/util/device.py
Final2x_core/util/progressLog.py
Final2x_core/util/singleton.py
final2x_core-4.0.0.dist-info/METADATA
final2x_core-4.0.0.dist-info/WHEEL
final2x_core-4.0.0.dist-info/entry_points.txt
final2x_core-4.0.0.dist-info/licenses/LICENSE
final2x_core-4.0.0.dist-info/RECORD
