Metadata-Version: 2.4
Name: Final2x_core
Version: 4.0.0
Summary: core library for Final2x
Project-URL: Homepage, https://github.com/EutropicAI/Final2x-core
Project-URL: Repository, https://github.com/EutropicAI/Final2x-core
Author: Tohrusky
License-Expression: BSD-3-Clause
License-File: LICENSE
Classifier: Programming Language :: Python :: 3.9
Classifier: Programming Language :: Python :: 3.10
Classifier: Programming Language :: Python :: 3.11
Classifier: Programming Language :: Python :: 3.12
Classifier: Programming Language :: Python :: 3.13
Requires-Python: <4,>=3.9
Requires-Dist: cccv==0.0.4
Requires-Dist: loguru
Requires-Dist: pydantic
Requires-Dist: pyyaml
